<?xml version="1.0"?>

<!--
Glider Vario,
David Culp, 29 Feb 2004, davidculp2@attbi.com,

This is an instrument configuration file for the open-source flight
simulator FlightGear (www.flightgear.org).  The file is an XML-encoded
FlightGear property list defining the instrument's layers and actions.

Each instrument is composed of layers stacked on top of each other.
A layer may be a texture (with transparent parts to show the layers
underneath), text, or a special layer that switches between two
others (say, to turn an indicator light on or off).  Each layer can
move independently in proportion to a property value, and text
can be generated from property values as well: all of the layer's
movements are defined as transformations.

Actions are hotspots on the instrument that will respond to a mouse
click.  Actions always modify the values of properties, either by
adjusting them, toggling them, or swaping them with other
properties' values.
-->

<PropertyList>
 <name>Vario</name>
 <w-base>51</w-base>
 <h-base>28</h-base>
 <layers>

  <layer>
   <name>background</name>
   <texture>
    <path>Aircraft/sgs233/Instruments/Textures/glider-misc.rgb</path>
    <x1>0.0</x1>
    <y1>0.890625</y1>
    <x2>0.1953125</x2>
    <y2>1.0</y2>
   </texture>
   <w>51</w>
   <h>28</h>
  </layer>

  <layer>
    <name>LED green</name>
    <condition>
     <greater-than>
      <property>velocities/vertical-speed-fps</property>
      <value>-0.00001</value>
     </greater-than>
    </condition>
    <type>text</type>
    <font>led</font>
    <point-size>6</point-size>
    <color>
     <red>0.70</red>
     <green>1.0</green>
     <blue>0.70</blue>
    </color>
    <chunks>
     <chunk>
      <type>number-value</type>
      <property>velocities/vertical-speed-fps</property>
      <scale>0.5924838</scale>
      <format>%2.1f</format>
     </chunk>
    </chunks>
    <transformations>
     <transformation>
      <type>x-shift</type>
      <offset>-18</offset>
     </transformation>
     <transformation>
      <type>y-shift</type>
      <offset>-6</offset>
     </transformation>
    </transformations>
  </layer>

  <layer>
    <name>LED red</name>
    <condition>
     <less-than>
      <property>velocities/vertical-speed-fps</property>
      <value>-0.00001</value>
     </less-than>
    </condition>
    <type>text</type>
    <font>led</font>
    <point-size>6</point-size>
    <color>
     <red>1.0</red>
     <green>0.70</green>
     <blue>0.70</blue>
    </color>
    <chunks>
     <chunk>
      <type>number-value</type>
      <property>velocities/vertical-speed-fps</property>
      <scale>0.5924838</scale>
      <format>%2.1f</format>
     </chunk>
    </chunks>
    <transformations>
     <transformation>
      <type>x-shift</type>
      <offset>-18</offset>
     </transformation>
     <transformation>
      <type>y-shift</type>
      <offset>-6</offset>
     </transformation>
    </transformations>
  </layer>


 </layers>
</PropertyList>
